[
  {
    "date": "2022-09-06T00:00:00.000Z",
    "currencies": [
      {
        "code": "AED",
        "quantity": 10,
        "rateFormated": "7.8396",
        "diffFormated": "0.0439",
        "rate": 7.8396,
        "name": "United Arab Emirates Dirhams",
        "diff": -0.0439,
        "date": "2022-09-05T17:45:13.670Z",
        "validFromDate": "2022-09-06T00:00:00.000Z"
      },
      {
        "code": "AMD",
        "quantity": 1000,
        "rateFormated": "7.1143",
        "diffFormated": "0.0530",
        "rate": 7.1143,
        "name": "Armenian Dram",
        "diff": -0.0530,
        "date": "2022-09-05T17:45:13.670Z",
        "validFromDate": "2022-09-06T00:00:00.000Z"
      },
      {
        "code": "AUD",
        "quantity": 1,
        "rateFormated": "1.9572",
        "diffFormated": "0.0133",
        "rate": 1.9572,
        "name": "Australian Dollar",
        "diff": -0.0133,
        "date": "2022-09-05T17:45:13.670Z",
        "validFromDate": "2022-09-06T00:00:00.000Z"
      },
      {
        "code": "AZN",
        "quantity": 1,
        "rateFormated": "1.6928",
        "diffFormated": "0.0154",
        "rate": 1.6928,
        "name": "Azerbaijan Manat",
        "diff": -0.0154,
        "date": "2022-09-05T17:45:13.670Z",
        "validFromDate": "2022-09-06T00:00:00.000Z"
      },
      {
        "code": "BGN",
        "quantity": 1,
        "rateFormated": "1.4623",
        "diffFormated": "0.0190",
        "rate": 1.4623,
        "name": "Bulgarian Lev",
        "diff": -0.0190,
        "date": "2022-09-05T17:45:13.670Z",
        "validFromDate": "2022-09-06T00:00:00.000Z"
      },
      {
        "code": "BRL",
        "quantity": 1,
        "rateFormated": "0.5569",
        "diffFormated": "0.0046",
        "rate": 0.5569,
        "name": "Brazilian Real",
        "diff": 0.0046,
        "date": "2022-09-05T17:45:13.670Z",
        "validFromDate": "2022-09-06T00:00:00.000Z"
      },
      {
        "code": "BYN",
        "quantity": 1,
        "rateFormated": "1.1435",
        "diffFormated": "0.0064",
        "rate": 1.1435,
        "name": "Belarusian Rouble",
        "diff": -0.0064,
        "date": "2022-09-05T17:45:13.670Z",
        "validFromDate": "2022-09-06T00:00:00.000Z"
      },
      {
        "code": "CAD",
        "quantity": 1,
        "rateFormated": "2.1897",
        "diffFormated": "0.0133",
        "rate": 2.1897,
        "name": "Canadian Dollar",
        "diff": -0.0133,
        "date": "2022-09-05T17:45:13.670Z",
        "validFromDate": "2022-09-06T00:00:00.000Z"
      },
      {
        "code": "CHF",
        "quantity": 1,
        "rateFormated": "2.9338",
        "diffFormated": "0.0140",
        "rate": 2.9338,
        "name": "Swiss Franc",
        "diff": -0.0140,
        "date": "2022-09-05T17:45:13.670Z",
        "validFromDate": "2022-09-06T00:00:00.000Z"
      },
      {
        "code": "CNY",
        "quantity": 10,
        "rateFormated": "4.1537",
        "diffFormated": "0.0385",
        "rate": 4.1537,
        "name": "China Renminbi",
        "diff": -0.0385,
        "date": "2022-09-05T17:45:13.670Z",
        "validFromDate": "2022-09-06T00:00:00.000Z"
      },
      {
        "code": "CZK",
        "quantity": 10,
        "rateFormated": "1.1619",
        "diffFormated": "0.0206",
        "rate": 1.1619,
        "name": "Czech Koruna",
        "diff": -0.0206,
        "date": "2022-09-05T17:45:13.670Z",
        "validFromDate": "2022-09-06T00:00:00.000Z"
      },
      {
        "code": "DKK",
        "quantity": 10,
        "rateFormated": "3.8457",
        "diffFormated": "0.0474",
        "rate": 3.8457,
        "name": "Danish Krone",
        "diff": -0.0474,
        "date": "2022-09-05T17:45:13.670Z",
        "validFromDate": "2022-09-06T00:00:00.000Z"
      },
      {
        "code": "EGP",
        "quantity": 10,
        "rateFormated": "1.4970",
        "diffFormated": "0.0087",
        "rate": 1.4970,
        "name": "Egyptian Pound",
        "diff": -0.0087,
        "date": "2022-09-05T17:45:13.670Z",
        "validFromDate": "2022-09-06T00:00:00.000Z"
      },
      {
        "code": "EUR",
        "quantity": 1,
        "rateFormated": "2.8599",
        "diffFormated": "0.0351",
        "rate": 2.8599,
        "name": "Euro",
        "diff": -0.0351,
        "date": "2022-09-05T17:45:13.670Z",
        "validFromDate": "2022-09-06T00:00:00.000Z"
      },
      {
        "code": "GBP",
        "quantity": 1,
        "rateFormated": "3.3152",
        "diffFormated": "0.0330",
        "rate": 3.3152,
        "name": "United Kingdom Pound",
        "diff": -0.0330,
        "date": "2022-09-05T17:45:13.670Z",
        "validFromDate": "2022-09-06T00:00:00.000Z"
      },
      {
        "code": "HKD",
        "quantity": 10,
        "rateFormated": "3.6686",
        "diffFormated": "0.0205",
        "rate": 3.6686,
        "name": "Hong-Kong Dollar",
        "diff": -0.0205,
        "date": "2022-09-05T17:45:13.670Z",
        "validFromDate": "2022-09-06T00:00:00.000Z"
      },
      {
        "code": "HUF",
        "quantity": 100,
        "rateFormated": "0.7070",
        "diffFormated": "0.0182",
        "rate": 0.7070,
        "name": "Hungarian Forint",
        "diff": -0.0182,
        "date": "2022-09-05T17:45:13.670Z",
        "validFromDate": "2022-09-06T00:00:00.000Z"
      },
      {
        "code": "ILS",
        "quantity": 10,
        "rateFormated": "8.4584",
        "diffFormated": "0.0621",
        "rate": 8.4584,
        "name": "Israeli Shekel",
        "diff": -0.0621,
        "date": "2022-09-05T17:45:13.670Z",
        "validFromDate": "2022-09-06T00:00:00.000Z"
      },
      {
        "code": "INR",
        "quantity": 100,
        "rateFormated": "3.6062",
        "diffFormated": "0.0223",
        "rate": 3.6062,
        "name": "Indian Rupee",
        "diff": -0.0223,
        "date": "2022-09-05T17:45:13.670Z",
        "validFromDate": "2022-09-06T00:00:00.000Z"
      },
      {
        "code": "IRR",
        "quantity": 10000,
        "rateFormated": "0.6856",
        "diffFormated": "0.0038",
        "rate": 0.6856,
        "name": "Iranian Rial",
        "diff": -0.0038,
        "date": "2022-09-05T17:45:13.670Z",
        "validFromDate": "2022-09-06T00:00:00.000Z"
      },
      {
        "code": "ISK",
        "quantity": 100,
        "rateFormated": "2.0016",
        "diffFormated": "0.0445",
        "rate": 2.0016,
        "name": "Iceland Krona",
        "diff": -0.0445,
        "date": "2022-09-05T17:45:13.670Z",
        "validFromDate": "2022-09-06T00:00:00.000Z"
      },
      {
        "code": "JPY",
        "quantity": 100,
        "rateFormated": "2.0500",
        "diffFormated": "0.0139",
        "rate": 2.0500,
        "name": "Japanese Yen",
        "diff": -0.0139,
        "date": "2022-09-05T17:45:13.670Z",
        "validFromDate": "2022-09-06T00:00:00.000Z"
      },
      {
        "code": "KGS",
        "quantity": 100,
        "rateFormated": "3.4909",
        "diffFormated": "0.0697",
        "rate": 3.4909,
        "name": "Kyrgyzstan Som",
        "diff": -0.0697,
        "date": "2022-09-05T17:45:13.670Z",
        "validFromDate": "2022-09-06T00:00:00.000Z"
      },
      {
        "code": "KRW",
        "quantity": 1000,
        "rateFormated": "2.0989",
        "diffFormated": "0.0255",
        "rate": 2.0989,
        "name": "South Korean Won",
        "diff": -0.0255,
        "date": "2022-09-05T17:45:13.670Z",
        "validFromDate": "2022-09-06T00:00:00.000Z"
      },
      {
        "code": "KWD",
        "quantity": 1,
        "rateFormated": "9.3339",
        "diffFormated": "0.0552",
        "rate": 9.3339,
        "name": "Kuwaiti Dinar",
        "diff": -0.0552,
        "date": "2022-09-05T17:45:13.670Z",
        "validFromDate": "2022-09-06T00:00:00.000Z"
      },
      {
        "code": "KZT",
        "quantity": 100,
        "rateFormated": "0.6098",
        "diffFormated": "0.0055",
        "rate": 0.6098,
        "name": "Kazakhstan Tenge",
        "diff": -0.0055,
        "date": "2022-09-05T17:45:13.670Z",
        "validFromDate": "2022-09-06T00:00:00.000Z"
      },
      {
        "code": "MDL",
        "quantity": 10,
        "rateFormated": "1.4853",
        "diffFormated": "0.0100",
        "rate": 1.4853,
        "name": "Moldova Lei",
        "diff": -0.0100,
        "date": "2022-09-05T17:45:13.670Z",
        "validFromDate": "2022-09-06T00:00:00.000Z"
      },
      {
        "code": "NOK",
        "quantity": 10,
        "rateFormated": "2.8801",
        "diffFormated": "0.0075",
        "rate": 2.8801,
        "name": "Norwegian Krone",
        "diff": -0.0075,
        "date": "2022-09-05T17:45:13.670Z",
        "validFromDate": "2022-09-06T00:00:00.000Z"
      },
      {
        "code": "NZD",
        "quantity": 1,
        "rateFormated": "1.7571",
        "diffFormated": "0.0069",
        "rate": 1.7571,
        "name": "New Zealand Dollar",
        "diff": -0.0069,
        "date": "2022-09-05T17:45:13.670Z",
        "validFromDate": "2022-09-06T00:00:00.000Z"
      },
      {
        "code": "PLN",
        "quantity": 10,
        "rateFormated": "6.0316",
        "diffFormated": "0.1146",
        "rate": 6.0316,
        "name": "Polish Zloty",
        "diff": -0.1146,
        "date": "2022-09-05T17:45:13.670Z",
        "validFromDate": "2022-09-06T00:00:00.000Z"
      },
      {
        "code": "QAR",
        "quantity": 10,
        "rateFormated": "7.8184",
        "diffFormated": "0.0524",
        "rate": 7.8184,
        "name": "Qatari Rial",
        "diff": -0.0524,
        "date": "2022-09-05T17:45:13.670Z",
        "validFromDate": "2022-09-06T00:00:00.000Z"
      },
      {
        "code": "RON",
        "quantity": 10,
        "rateFormated": "5.9325",
        "diffFormated": "0.0598",
        "rate": 5.9325,
        "name": "Romanian Leu",
        "diff": -0.0598,
        "date": "2022-09-05T17:45:13.670Z",
        "validFromDate": "2022-09-06T00:00:00.000Z"
      },
      {
        "code": "RSD",
        "quantity": 100,
        "rateFormated": "2.4377",
        "diffFormated": "0.0294",
        "rate": 2.4377,
        "name": "Serbian Dinar",
        "diff": -0.0294,
        "date": "2022-09-05T17:45:13.670Z",
        "validFromDate": "2022-09-06T00:00:00.000Z"
      },
      {
        "code": "RUB",
        "quantity": 100,
        "rateFormated": "4.7132",
        "diffFormated": "0.0522",
        "rate": 4.7132,
        "name": "Russian Ruble",
        "diff": -0.0522,
        "date": "2022-09-05T17:45:13.670Z",
        "validFromDate": "2022-09-06T00:00:00.000Z"
      },
      {
        "code": "SEK",
        "quantity": 10,
        "rateFormated": "2.6655",
        "diffFormated": "0.0273",
        "rate": 2.6655,
        "name": "Swedish Krona",
        "diff": -0.0273,
        "date": "2022-09-05T17:45:13.670Z",
        "validFromDate": "2022-09-06T00:00:00.000Z"
      },
      {
        "code": "SGD",
        "quantity": 1,
        "rateFormated": "2.0505",
        "diffFormated": "0.0151",
        "rate": 2.0505,
        "name": "Singapore Dollar",
        "diff": -0.0151,
        "date": "2022-09-05T17:45:13.670Z",
        "validFromDate": "2022-09-06T00:00:00.000Z"
      },
      {
        "code": "TJS",
        "quantity": 10,
        "rateFormated": "2.8259",
        "diffFormated": "0.0109",
        "rate": 2.8259,
        "name": "Tajikistan Somoni",
        "diff": -0.0109,
        "date": "2022-09-05T17:45:13.670Z",
        "validFromDate": "2022-09-06T00:00:00.000Z"
      },
      {
        "code": "TMT",
        "quantity": 10,
        "rateFormated": "8.2271",
        "diffFormated": "0.0460",
        "rate": 8.2271,
        "name": "Turkmenistan Manat",
        "diff": -0.0460,
        "date": "2022-09-05T17:45:13.670Z",
        "validFromDate": "2022-09-06T00:00:00.000Z"
      },
      {
        "code": "TRY",
        "quantity": 1,
        "rateFormated": "0.1580",
        "diffFormated": "0.0009",
        "rate": 0.1580,
        "name": "Turkish Lira",
        "diff": -0.0009,
        "date": "2022-09-05T17:45:13.670Z",
        "validFromDate": "2022-09-06T00:00:00.000Z"
      },
      {
        "code": "UAH",
        "quantity": 10,
        "rateFormated": "0.7797",
        "diffFormated": "0.0044",
        "rate": 0.7797,
        "name": "Ukraine Hryvna",
        "diff": -0.0044,
        "date": "2022-09-05T17:45:13.670Z",
        "validFromDate": "2022-09-06T00:00:00.000Z"
      },
      {
        "code": "USD",
        "quantity": 1,
        "rateFormated": "2.8795",
        "diffFormated": "0.0161",
        "rate": 2.8795,
        "name": "US Dollar",
        "diff": -0.0161,
        "date": "2022-09-05T17:45:13.670Z",
        "validFromDate": "2022-09-06T00:00:00.000Z"
      },
      {
        "code": "UZS",
        "quantity": 1000,
        "rateFormated": "0.2634",
        "diffFormated": "0.0009",
        "rate": 0.2634,
        "name": "Uzbekistan Sum",
        "diff": -0.0009,
        "date": "2022-09-05T17:45:13.670Z",
        "validFromDate": "2022-09-06T00:00:00.000Z"
      },
      {
        "code": "ZAR",
        "quantity": 10,
        "rateFormated": "1.6673",
        "diffFormated": "0.0039",
        "rate": 1.6673,
        "name": "South African Rand",
        "diff": -0.0039,
        "date": "2022-09-05T17:45:13.670Z",
        "validFromDate": "2022-09-06T00:00:00.000Z"
      }
    ]
  }
]